coddj/__init__.py
coddj/__main__.py
coddj/coddj.py
coddj/player.py
coddj/search.py
coddj-0.1.2.dist-info/LICENSE
coddj-0.1.2.dist-info/METADATA
coddj-0.1.2.dist-info/WHEEL
coddj-0.1.2.dist-info/RECORD
